guzi/__init__.py
guzi/models.py
python-guzi/__init__.py
tests/__init__.py
tests/test_models.py
guzi-0.0.4.dist-info/LICENSE
guzi-0.0.4.dist-info/METADATA
guzi-0.0.4.dist-info/WHEEL
guzi-0.0.4.dist-info/top_level.txt
guzi-0.0.4.dist-info/RECORD
